{
  "generatedAt": "2026-06-09T17:34:34.802Z",
  "sims": 20000,
  "model": {
    "tempering": 0.8,
    "ratings": "elo_historico + jogos da Copa (Elo ao vivo)",
    "groupStage": "exato (desempates FIFA: pts, saldo, gols, confronto direto); resultados já ocorridos são fixados",
    "knockout": "tabela oficial FIFA 2026 (jogos 73–104); 3ºs por matching nos grupos permitidos; jogos já decididos são travados"
  },
  "teams": [
    {
      "id": 760,
      "name": "Spain",
      "tla": "ESP",
      "crest": "https://crests.football-data.org/760.svg",
      "group": "H",
      "elo": 2211,
      "pChampion": 20.3,
      "pFinal": 29.9,
      "pSemi": 42.9,
      "pQuarter": 54.9,
      "pR16": 74.9,
      "pAdvance": 99.7,
      "pWinGroup": 81
    },
    {
      "id": 762,
      "name": "Argentina",
      "tla": "ARG",
      "crest": "https://crests.football-data.org/762.png",
      "group": "J",
      "elo": 2178,
      "pChampion": 14.9,
      "pFinal": 24.1,
      "pSemi": 36.5,
      "pQuarter": 51.7,
      "pR16": 67.7,
      "pAdvance": 98.4,
      "pWinGroup": 78.2
    },
    {
      "id": 773,
      "name": "France",
      "tla": "FRA",
      "crest": "https://crests.football-data.org/773.svg",
      "group": "I",
      "elo": 2121,
      "pChampion": 9.8,
      "pFinal": 16.8,
      "pSemi": 29.5,
      "pQuarter": 46.4,
      "pR16": 69.5,
      "pAdvance": 95.8,
      "pWinGroup": 61.1
    },
    {
      "id": 770,
      "name": "England",
      "tla": "ENG",
      "crest": "https://crests.football-data.org/770.svg",
      "group": "L",
      "elo": 2084,
      "pChampion": 6,
      "pFinal": 12.2,
      "pSemi": 22.4,
      "pQuarter": 37.9,
      "pR16": 65.2,
      "pAdvance": 97.7,
      "pWinGroup": 61.4
    },
    {
      "id": 769,
      "name": "Mexico",
      "tla": "MEX",
      "crest": "https://crests.football-data.org/769.svg",
      "group": "A",
      "elo": 1966,
      "pChampion": 5.1,
      "pFinal": 10.2,
      "pSemi": 20.3,
      "pQuarter": 37.6,
      "pR16": 65.1,
      "pAdvance": 96.7,
      "pWinGroup": 65.7
    },
    {
      "id": 764,
      "name": "Brazil",
      "tla": "BRA",
      "crest": "https://crests.football-data.org/764.svg",
      "group": "C",
      "elo": 2057,
      "pChampion": 4.6,
      "pFinal": 9.6,
      "pSemi": 19.6,
      "pQuarter": 34.9,
      "pR16": 57.4,
      "pAdvance": 94.5,
      "pWinGroup": 53.1
    },
    {
      "id": 818,
      "name": "Colombia",
      "tla": "COL",
      "crest": "https://crests.football-data.org/818.svg",
      "group": "K",
      "elo": 2053,
      "pChampion": 4.5,
      "pFinal": 9.5,
      "pSemi": 17.5,
      "pQuarter": 32.2,
      "pR16": 58.1,
      "pAdvance": 92.3,
      "pWinGroup": 46.5
    },
    {
      "id": 765,
      "name": "Portugal",
      "tla": "POR",
      "crest": "https://crests.football-data.org/765.svg",
      "group": "K",
      "elo": 2036,
      "pChampion": 3.8,
      "pFinal": 8.1,
      "pSemi": 15.5,
      "pQuarter": 29.6,
      "pR16": 56,
      "pAdvance": 91.3,
      "pWinGroup": 42.3
    },
    {
      "id": 791,
      "name": "Ecuador",
      "tla": "ECU",
      "crest": "https://crests.football-data.org/791.svg",
      "group": "E",
      "elo": 2016,
      "pChampion": 3.1,
      "pFinal": 7,
      "pSemi": 15.6,
      "pQuarter": 30,
      "pR16": 58.2,
      "pAdvance": 95,
      "pWinGroup": 46.1
    },
    {
      "id": 8601,
      "name": "Netherlands",
      "tla": "NED",
      "crest": "https://crests.football-data.org/8601.svg",
      "group": "F",
      "elo": 2010,
      "pChampion": 2.8,
      "pFinal": 6.3,
      "pSemi": 13.7,
      "pQuarter": 27.7,
      "pR16": 49.4,
      "pAdvance": 91.9,
      "pWinGroup": 45.7
    },
    {
      "id": 759,
      "name": "Germany",
      "tla": "GER",
      "crest": "https://crests.football-data.org/759.svg",
      "group": "E",
      "elo": 2010,
      "pChampion": 2.7,
      "pFinal": 6.6,
      "pSemi": 14.7,
      "pQuarter": 29.2,
      "pR16": 57.2,
      "pAdvance": 94.9,
      "pWinGroup": 44.1
    },
    {
      "id": 828,
      "name": "Canada",
      "tla": "CAN",
      "crest": "https://crests.football-data.org/canada.svg",
      "group": "B",
      "elo": 1899,
      "pChampion": 2.6,
      "pFinal": 6.1,
      "pSemi": 13.4,
      "pQuarter": 30.4,
      "pR16": 61.4,
      "pAdvance": 97.4,
      "pWinGroup": 54.5
    },
    {
      "id": 766,
      "name": "Japan",
      "tla": "JPN",
      "crest": "https://crests.football-data.org/766.svg",
      "group": "F",
      "elo": 2000,
      "pChampion": 2.3,
      "pFinal": 5.6,
      "pSemi": 12.7,
      "pQuarter": 25.9,
      "pR16": 47.1,
      "pAdvance": 91.1,
      "pWinGroup": 43.2
    },
    {
      "id": 815,
      "name": "Morocco",
      "tla": "MAR",
      "crest": "https://crests.football-data.org/morocco.svg",
      "group": "C",
      "elo": 1990,
      "pChampion": 2.2,
      "pFinal": 5.2,
      "pSemi": 11.9,
      "pQuarter": 24.5,
      "pR16": 46.8,
      "pAdvance": 88.8,
      "pWinGroup": 33.9
    },
    {
      "id": 8872,
      "name": "Norway",
      "tla": "NOR",
      "crest": "https://crests.football-data.org/813.svg",
      "group": "I",
      "elo": 1972,
      "pChampion": 1.7,
      "pFinal": 4.2,
      "pSemi": 9.9,
      "pQuarter": 21.5,
      "pR16": 43.1,
      "pAdvance": 79.9,
      "pWinGroup": 22.6
    },
    {
      "id": 788,
      "name": "Switzerland",
      "tla": "SUI",
      "crest": "https://crests.football-data.org/788.svg",
      "group": "B",
      "elo": 1947,
      "pChampion": 1.7,
      "pFinal": 4.3,
      "pSemi": 10.5,
      "pQuarter": 25.1,
      "pR16": 55.4,
      "pAdvance": 95.7,
      "pWinGroup": 42
    },
    {
      "id": 758,
      "name": "Uruguay",
      "tla": "URY",
      "crest": "https://crests.football-data.org/758.svg",
      "group": "H",
      "elo": 1964,
      "pChampion": 1.6,
      "pFinal": 4.1,
      "pSemi": 9.5,
      "pQuarter": 19.4,
      "pR16": 36.9,
      "pAdvance": 91.2,
      "pWinGroup": 17.5
    },
    {
      "id": 803,
      "name": "Turkey",
      "tla": "TUR",
      "crest": "https://crests.football-data.org/803.svg",
      "group": "D",
      "elo": 1969,
      "pChampion": 1.5,
      "pFinal": 4,
      "pSemi": 9.1,
      "pQuarter": 22.5,
      "pR16": 46.2,
      "pAdvance": 77.5,
      "pWinGroup": 33.5
    },
    {
      "id": 799,
      "name": "Croatia",
      "tla": "CRO",
      "crest": "https://crests.football-data.org/799.svg",
      "group": "L",
      "elo": 1962,
      "pChampion": 1.5,
      "pFinal": 3.9,
      "pSemi": 9.2,
      "pQuarter": 20,
      "pR16": 45.9,
      "pAdvance": 89.1,
      "pWinGroup": 28.1
    },
    {
      "id": 805,
      "name": "Belgium",
      "tla": "BEL",
      "crest": "https://crests.football-data.org/805.svg",
      "group": "G",
      "elo": 1955,
      "pChampion": 1.4,
      "pFinal": 3.8,
      "pSemi": 9,
      "pQuarter": 24.3,
      "pR16": 50.9,
      "pAdvance": 89.5,
      "pWinGroup": 47.7
    },
    {
      "id": 771,
      "name": "United States",
      "tla": "USA",
      "crest": "https://crests.football-data.org/usa.svg",
      "group": "D",
      "elo": 1845,
      "pChampion": 1.2,
      "pFinal": 2.7,
      "pSemi": 6.6,
      "pQuarter": 17.1,
      "pR16": 38.1,
      "pAdvance": 70.2,
      "pWinGroup": 25.3
    },
    {
      "id": 761,
      "name": "Paraguay",
      "tla": "PAR",
      "crest": "https://crests.football-data.org/761.svg",
      "group": "D",
      "elo": 1908,
      "pChampion": 0.6,
      "pFinal": 1.6,
      "pSemi": 4.7,
      "pQuarter": 13.8,
      "pR16": 33.6,
      "pAdvance": 65.1,
      "pWinGroup": 21.5
    },
    {
      "id": 804,
      "name": "Senegal",
      "tla": "SEN",
      "crest": "https://crests.football-data.org/senegal.svg",
      "group": "I",
      "elo": 1908,
      "pChampion": 0.6,
      "pFinal": 2,
      "pSemi": 5.5,
      "pQuarter": 14,
      "pR16": 31.9,
      "pAdvance": 68,
      "pWinGroup": 13.8
    },
    {
      "id": 779,
      "name": "Australia",
      "tla": "AUS",
      "crest": "https://crests.football-data.org/779.svg",
      "group": "D",
      "elo": 1902,
      "pChampion": 0.6,
      "pFinal": 1.8,
      "pSemi": 4.6,
      "pQuarter": 13.3,
      "pR16": 32.1,
      "pAdvance": 63.2,
      "pWinGroup": 19.7
    },
    {
      "id": 840,
      "name": "Iran",
      "tla": "IRN",
      "crest": "https://crests.football-data.org/iran.svg",
      "group": "G",
      "elo": 1894,
      "pChampion": 0.5,
      "pFinal": 1.8,
      "pSemi": 5.2,
      "pQuarter": 15.6,
      "pR16": 39.1,
      "pAdvance": 81.3,
      "pWinGroup": 31
    },
    {
      "id": 772,
      "name": "South Korea",
      "tla": "KOR",
      "crest": "https://crests.football-data.org/772.png",
      "group": "A",
      "elo": 1883,
      "pChampion": 0.5,
      "pFinal": 1.6,
      "pSemi": 5.5,
      "pQuarter": 15.5,
      "pR16": 39.4,
      "pAdvance": 80.7,
      "pWinGroup": 21.3
    },
    {
      "id": 816,
      "name": "Austria",
      "tla": "AUT",
      "crest": "https://crests.football-data.org/816.svg",
      "group": "J",
      "elo": 1893,
      "pChampion": 0.4,
      "pFinal": 1.3,
      "pSemi": 3.6,
      "pQuarter": 9.6,
      "pR16": 21.8,
      "pAdvance": 67.5,
      "pWinGroup": 10.9
    },
    {
      "id": 778,
      "name": "Algeria",
      "tla": "ALG",
      "crest": "https://crests.football-data.org/algeria.svg",
      "group": "J",
      "elo": 1873,
      "pChampion": 0.3,
      "pFinal": 1,
      "pSemi": 3,
      "pQuarter": 8.6,
      "pR16": 19.9,
      "pAdvance": 62,
      "pWinGroup": 8.2
    },
    {
      "id": 8873,
      "name": "Scotland",
      "tla": "SCO",
      "crest": "https://crests.football-data.org/814.svg",
      "group": "C",
      "elo": 1849,
      "pChampion": 0.3,
      "pFinal": 0.9,
      "pSemi": 2.9,
      "pQuarter": 8.5,
      "pR16": 22.4,
      "pAdvance": 62.6,
      "pWinGroup": 10.8
    },
    {
      "id": 1836,
      "name": "Panama",
      "tla": "PAN",
      "crest": "https://crests.football-data.org/panama.svg",
      "group": "L",
      "elo": 1838,
      "pChampion": 0.2,
      "pFinal": 0.8,
      "pSemi": 2.6,
      "pQuarter": 7.6,
      "pR16": 23.4,
      "pAdvance": 67.3,
      "pWinGroup": 9.8
    },
    {
      "id": 1935,
      "name": "Ivory Coast",
      "tla": "CIV",
      "crest": "https://crests.football-data.org/787.svg",
      "group": "E",
      "elo": 1809,
      "pChampion": 0.2,
      "pFinal": 0.7,
      "pSemi": 2.3,
      "pQuarter": 7.7,
      "pR16": 23.5,
      "pAdvance": 64.8,
      "pWinGroup": 9.1
    },
    {
      "id": 8070,
      "name": "Uzbekistan",
      "tla": "UZB",
      "crest": "https://crests.football-data.org/8070.png",
      "group": "K",
      "elo": 1821,
      "pChampion": 0.1,
      "pFinal": 0.5,
      "pSemi": 1.7,
      "pQuarter": 5.1,
      "pR16": 16.9,
      "pAdvance": 50.5,
      "pWinGroup": 7.4
    },
    {
      "id": 798,
      "name": "Czechia",
      "tla": "CZE",
      "crest": "https://crests.football-data.org/798.svg",
      "group": "A",
      "elo": 1802,
      "pChampion": 0.1,
      "pFinal": 0.5,
      "pSemi": 2,
      "pQuarter": 8,
      "pR16": 24.7,
      "pAdvance": 62.8,
      "pWinGroup": 10.6
    },
    {
      "id": 825,
      "name": "Egypt",
      "tla": "EGY",
      "crest": "https://crests.football-data.org/825.svg",
      "group": "G",
      "elo": 1797,
      "pChampion": 0.1,
      "pFinal": 0.4,
      "pSemi": 1.5,
      "pQuarter": 6.4,
      "pR16": 22.3,
      "pAdvance": 61.7,
      "pWinGroup": 14.4
    },
    {
      "id": 8049,
      "name": "Jordan",
      "tla": "JOR",
      "crest": "https://crests.football-data.org/8049.png",
      "group": "J",
      "elo": 1769,
      "pChampion": 0,
      "pFinal": 0.1,
      "pSemi": 0.6,
      "pQuarter": 2.7,
      "pR16": 8.3,
      "pAdvance": 35.5,
      "pWinGroup": 2.7
    },
    {
      "id": 792,
      "name": "Sweden",
      "tla": "SWE",
      "crest": "https://crests.football-data.org/792.svg",
      "group": "F",
      "elo": 1765,
      "pChampion": 0,
      "pFinal": 0.2,
      "pSemi": 0.8,
      "pQuarter": 3.5,
      "pR16": 12.5,
      "pAdvance": 45.9,
      "pWinGroup": 6.3
    },
    {
      "id": 1934,
      "name": "Congo DR",
      "tla": "COD",
      "crest": "https://crests.football-data.org/congo_dr.svg",
      "group": "K",
      "elo": 1762,
      "pChampion": 0,
      "pFinal": 0.1,
      "pSemi": 0.6,
      "pQuarter": 2.4,
      "pR16": 9.2,
      "pAdvance": 33.8,
      "pWinGroup": 3.9
    },
    {
      "id": 8062,
      "name": "Iraq",
      "tla": "IRQ",
      "crest": "https://crests.football-data.org/iraq.svg",
      "group": "I",
      "elo": 1749,
      "pChampion": 0,
      "pFinal": 0.1,
      "pSemi": 0.5,
      "pQuarter": 2.1,
      "pR16": 7.5,
      "pAdvance": 26,
      "pWinGroup": 2.6
    },
    {
      "id": 802,
      "name": "Tunisia",
      "tla": "TUN",
      "crest": "https://crests.football-data.org/tunisia.svg",
      "group": "F",
      "elo": 1741,
      "pChampion": 0,
      "pFinal": 0.1,
      "pSemi": 0.6,
      "pQuarter": 2.5,
      "pR16": 9.9,
      "pAdvance": 39.2,
      "pWinGroup": 4.8
    },
    {
      "id": 783,
      "name": "New Zealand",
      "tla": "NZL",
      "crest": "https://crests.football-data.org/783.svg",
      "group": "G",
      "elo": 1721,
      "pChampion": 0,
      "pFinal": 0.1,
      "pSemi": 0.5,
      "pQuarter": 2.4,
      "pR16": 11.1,
      "pAdvance": 40.4,
      "pWinGroup": 6.9
    },
    {
      "id": 836,
      "name": "Haiti",
      "tla": "HAI",
      "crest": "https://crests.football-data.org/haiti.svg",
      "group": "C",
      "elo": 1699,
      "pChampion": 0,
      "pFinal": 0,
      "pSemi": 0.2,
      "pQuarter": 1.2,
      "pR16": 5.2,
      "pAdvance": 24,
      "pWinGroup": 2.2
    },
    {
      "id": 801,
      "name": "Saudi Arabia",
      "tla": "KSA",
      "crest": "https://crests.football-data.org/saudi_arabia.svg",
      "group": "H",
      "elo": 1692,
      "pChampion": 0,
      "pFinal": 0,
      "pSemi": 0.2,
      "pQuarter": 1.5,
      "pR16": 6.5,
      "pAdvance": 34.3,
      "pWinGroup": 0.9
    },
    {
      "id": 774,
      "name": "South Africa",
      "tla": "RSA",
      "crest": "https://crests.football-data.org/9396.svg",
      "group": "A",
      "elo": 1664,
      "pChampion": 0,
      "pFinal": 0,
      "pSemi": 0.3,
      "pQuarter": 1.6,
      "pR16": 7.3,
      "pAdvance": 27.9,
      "pWinGroup": 2.4
    },
    {
      "id": 1930,
      "name": "Cape Verde Islands",
      "tla": "CPV",
      "crest": "https://crests.football-data.org/cape_verde.svg",
      "group": "H",
      "elo": 1644,
      "pChampion": 0,
      "pFinal": 0,
      "pSemi": 0.1,
      "pQuarter": 0.8,
      "pR16": 3.8,
      "pAdvance": 24.8,
      "pWinGroup": 0.6
    },
    {
      "id": 1060,
      "name": "Bosnia-Herzegovina",
      "tla": "BIH",
      "crest": "https://crests.football-data.org/bosnia.svg",
      "group": "B",
      "elo": 1637,
      "pChampion": 0,
      "pFinal": 0,
      "pSemi": 0.2,
      "pQuarter": 1.6,
      "pR16": 8.6,
      "pAdvance": 39.9,
      "pWinGroup": 2.5
    },
    {
      "id": 763,
      "name": "Ghana",
      "tla": "GHA",
      "crest": "https://crests.football-data.org/ghana.svg",
      "group": "L",
      "elo": 1625,
      "pChampion": 0,
      "pFinal": 0,
      "pSemi": 0.1,
      "pQuarter": 0.4,
      "pR16": 2.2,
      "pAdvance": 14.5,
      "pWinGroup": 0.7
    },
    {
      "id": 9460,
      "name": "Curaçao",
      "tla": "CUW",
      "crest": "https://crests.football-data.org/curacao.svg",
      "group": "E",
      "elo": 1604,
      "pChampion": 0,
      "pFinal": 0,
      "pSemi": 0,
      "pQuarter": 0.5,
      "pR16": 2.4,
      "pAdvance": 13.7,
      "pWinGroup": 0.6
    },
    {
      "id": 8030,
      "name": "Qatar",
      "tla": "QAT",
      "crest": "https://crests.football-data.org/8030.svg",
      "group": "B",
      "elo": 1573,
      "pChampion": 0,
      "pFinal": 0,
      "pSemi": 0.1,
      "pQuarter": 0.7,
      "pR16": 4,
      "pAdvance": 23.9,
      "pWinGroup": 1
    }
  ]
}